bdaklr/__init__.py
bdaklr/bdaklr.py
bdaklr-0.1.dist-info/METADATA
bdaklr-0.1.dist-info/WHEEL
bdaklr-0.1.dist-info/top_level.txt
bdaklr-0.1.dist-info/RECORD
